{
  "version": "1.0",
  "predictive_scheduling": {
    "task_duration_prediction": {
      "model_type": "regression",
      "features": [
        "task_type",
        "complexity",
        "dependencies",
        "historical_data"
      ],
      "accuracy_target": 0.85
    },
    "optimal_timing": {
      "peak_productivity_hours": ["09:00-12:00", "14:00-17:00"],
      "resource_availability": true,
      "team_scheduling": true
    },
    "dependency_optimization": {
      "parallel_execution": true,
      "critical_path_analysis": true,
      "bottleneck_prevention": true
    }
  },
  "historical_data": {
    "task_completions": [],
    "duration_patterns": [],
    "success_rates": []
  }
}
